setup.py
probability_mk/Binomialdistribution.py
probability_mk/Gaussiandistribution.py
probability_mk/Generaldistribution.py
probability_mk/__init__.py
probability_mk.egg-info/PKG-INFO
probability_mk.egg-info/SOURCES.txt
probability_mk.egg-info/dependency_links.txt
probability_mk.egg-info/not-zip-safe
probability_mk.egg-info/top_level.txt