Metadata-Version: 1.0
Name: probability-mk
Version: 0.1
Summary: Gaussian and Binomial distributions
Home-page: UNKNOWN
Author: Mikel Alberdi
Author-email: mikelalberdi131@gmail.com
License: UNKNOWN
Platform: UNKNOWN
